link/__init__.py
link/mongo/__init__.py
link/mongo/driver.py
link/mongo/model.py
link/mongo/storage.py
link/mongo/ast/__init__.py
link/mongo/ast/filter.py
link/mongo/ast/insert.py
link.mongo-0.10.dist-info/DESCRIPTION.rst
link.mongo-0.10.dist-info/METADATA
link.mongo-0.10.dist-info/RECORD
link.mongo-0.10.dist-info/WHEEL
link.mongo-0.10.dist-info/metadata.json
link.mongo-0.10.dist-info/top_level.txt
