Metadata-Version: 2.0
Name: link.mongo
Version: 0.10
Summary: MongoDB for link.dbrequest
Home-page: https://github.com/linkdd/link.mongo
Author: David Delassus
Author-email: david.jose.delassus@gmail.com
License: MIT
Keywords: link database request mongodb
Platform: UNKNOWN
Classifier: Development Status :: 3 - Alpha
Classifier: License :: OSI Approved :: MIT License
Classifier: Operating System :: OS Independent
Classifier: Topic :: Utilities
Classifier: Topic :: Software Development :: Libraries :: Python Modules
Classifier: Intended Audience :: Developers
Classifier: Programming Language :: Python
Classifier: Programming Language :: Python :: 2.7
Classifier: Programming Language :: Python :: 3
Classifier: Programming Language :: Python :: 3.4
Classifier: Programming Language :: Python :: 3.5
Classifier: Programming Language :: Python :: Implementation :: CPython
Requires-Dist: b3j0f.conf (>=0.3.19)
Requires-Dist: b3j0f.task (>=0.0.4)
Requires-Dist: link.dbrequest (>=0.19)
Requires-Dist: pymongo (>=3.2.2)
Requires-Dist: six (>=1.10.0)
